{
    "Air_30kW": {
        "eta_s": {
            "-20": {
                "15": 0.55,
                "20": 0.56,
                "25": 0.56,
                "30": 0.55,
                "35": 0.42,
                "40": 0.45,
                "45": 0.35,
                "50": null,
                "55": null,
                "60": null
            },
            "-15": {
                "15": 0.54,
                "20": 0.56,
                "25": 0.58,
                "30": 0.58,
                "35": 0.52,
                "40": 0.54,
                "45": 0.48,
                "50": null,
                "55": null,
                "60": null
            },
            "-12": {
                "15": 0.54,
                "20": 0.56,
                "25": 0.58,
                "30": 0.59,
                "35": 0.56,
                "40": 0.57,
                "45": 0.54,
                "50": null,
                "55": null,
                "60": null
            },
            "-10": {
                "15": 0.53,
                "20": 0.56,
                "25": 0.58,
                "30": 0.6,
                "35": 0.58,
                "40": 0.59,
                "45": 0.57,
                "50": 0.52,
                "55": null,
                "60": null
            },
            "-7": {
                "15": 0.51,
                "20": 0.54,
                "25": 0.58,
                "30": 0.6,
                "35": 0.61,
                "40": 0.62,
                "45": 0.61,
                "50": 0.58,
                "55": 0.61,
                "60": null
            },
            "-2": {
                "15": 0.47,
                "20": 0.52,
                "25": 0.56,
                "30": 0.59,
                "35": 0.63,
                "40": 0.64,
                "45": 0.65,
                "50": 0.65,
                "55": 0.67,
                "60": 0.59
            },
            "2": {
                "15": 0.44,
                "20": 0.49,
                "25": 0.53,
                "30": 0.58,
                "35": 0.63,
                "40": 0.65,
                "45": 0.67,
                "50": 0.69,
                "55": 0.69,
                "60": 0.69
            },
            "7": {
                "15": 0.41,
                "20": 0.45,
                "25": 0.5,
                "30": 0.55,
                "35": 0.63,
                "40": 0.64,
                "45": 0.68,
                "50": 0.71,
                "55": 0.77,
                "60": 0.78
            },
            "10": {
                "15": 0.4,
                "20": 0.43,
                "25": 0.48,
                "30": 0.53,
                "35": 0.65,
                "40": 0.63,
                "45": 0.67,
                "50": 0.72,
                "55": 0.77,
                "60": 0.81
            },
            "12": {
                "15": 0.43,
                "20": 0.41,
                "25": 0.46,
                "30": 0.51,
                "35": 0.62,
                "40": 0.62,
                "45": 0.67,
                "50": 0.72,
                "55": 0.8,
                "60": 0.83
            },
            "15": {
                "15": null,
                "20": 0.41,
                "25": 0.44,
                "30": 0.49,
                "35": 0.59,
                "40": 0.6,
                "45": 0.65,
                "50": 0.71,
                "55": 0.79,
                "60": 0.85
            },
            "20": {
                "15": null,
                "20": null,
                "25": 0.42,
                "30": 0.45,
                "35": 0.53,
                "40": 0.56,
                "45": 0.62,
                "50": 0.69,
                "55": 0.74,
                "60": 0.86
            },
            "25": {
                "15": null,
                "20": null,
                "25": null,
                "30": 0.42,
                "35": 0.45,
                "40": 0.52,
                "45": 0.58,
                "50": 0.66,
                "55": 0.68,
                "60": 0.84
            },
            "30": {
                "15": null,
                "20": null,
                "25": null,
                "30": null,
                "35": 0.37,
                "40": 0.47,
                "45": 0.54,
                "50": 0.61,
                "55": 0.62,
                "60": 0.81
            },
            "35": {
                "15": null,
                "20": null,
                "25": null,
                "30": null,
                "35": null,
                "40": 0.45,
                "45": 0.49,
                "50": 0.56,
                "55": 0.56,
                "60": 0.77
            }
        },
        "heatload": {
            "-20": {
                "15": 15.8,
                "20": 15.8,
                "25": 15.8,
                "30": 15.8,
                "35": 15.8,
                "40": 15.8,
                "45": 15.8,
                "50": null,
                "55": null,
                "60": null
            },
            "-15": {
                "15": 19.0,
                "20": 19.0,
                "25": 19.0,
                "30": 19.0,
                "35": 19.0,
                "40": 19.0,
                "45": 19.0,
                "50": null,
                "55": null,
                "60": null
            },
            "-12": {
                "15": 21.0,
                "20": 21.0,
                "25": 21.0,
                "30": 21.0,
                "35": 21.0,
                "40": 21.0,
                "45": 21.0,
                "50": null,
                "55": null,
                "60": null
            },
            "-10": {
                "15": 22.3,
                "20": 22.3,
                "25": 22.3,
                "30": 22.3,
                "35": 22.3,
                "40": 22.3,
                "45": 22.3,
                "50": 22.3,
                "55": null,
                "60": null
            },
            "-7": {
                "15": 24.28,
                "20": 24.28,
                "25": 24.28,
                "30": 24.28,
                "35": 24.28,
                "40": 24.28,
                "45": 24.28,
                "50": 24.28,
                "55": 24.28,
                "60": null
            },
            "-2": {
                "15": 27.1,
                "20": 27.1,
                "25": 27.1,
                "30": 27.1,
                "35": 27.2,
                "40": 27.1,
                "45": 27.1,
                "50": 27.1,
                "55": 27.0,
                "60": 27.1
            },
            "2": {
                "15": 29.39,
                "20": 29.39,
                "25": 29.39,
                "30": 29.39,
                "35": 29.67,
                "40": 29.39,
                "45": 29.39,
                "50": 29.39,
                "55": 29.1,
                "60": 29.39
            },
            "7": {
                "15": 33.25,
                "20": 33.25,
                "25": 33.25,
                "30": 33.25,
                "35": 32.5,
                "40": 33.25,
                "45": 33.25,
                "50": 33.25,
                "55": 34.0,
                "60": 33.25
            },
            "10": {
                "15": 38.47,
                "20": 38.47,
                "25": 38.47,
                "30": 38.47,
                "35": 39.43,
                "40": 38.47,
                "45": 38.47,
                "50": 38.47,
                "55": 37.5,
                "60": 38.47
            },
            "12": {
                "15": 40.5,
                "20": 40.5,
                "25": 40.5,
                "30": 40.5,
                "35": 40.5,
                "40": 40.5,
                "45": 40.5,
                "50": 40.5,
                "55": 40.5,
                "60": 40.5
            },
            "15": {
                "15": null,
                "20": 42.4,
                "25": 42.4,
                "30": 42.4,
                "35": 42.4,
                "40": 42.4,
                "45": 42.4,
                "50": 42.4,
                "55": 42.4,
                "60": 42.4
            },
            "20": {
                "15": null,
                "20": null,
                "25": 45.1,
                "30": 45.1,
                "35": 45.1,
                "40": 45.1,
                "45": 45.1,
                "50": 45.1,
                "55": 45.1,
                "60": 45.1
            },
            "25": {
                "15": null,
                "20": null,
                "25": null,
                "30": 48.0,
                "35": 48.0,
                "40": 48.0,
                "45": 48.0,
                "50": 48.0,
                "55": 48.0,
                "60": 48.0
            },
            "30": {
                "15": null,
                "20": null,
                "25": null,
                "30": null,
                "35": 51.0,
                "40": 51.0,
                "45": 51.0,
                "50": 51.0,
                "55": 51.0,
                "60": 51.0
            },
            "35": {
                "15": null,
                "20": null,
                "25": null,
                "30": null,
                "35": null,
                "40": 54.0,
                "45": 54.0,
                "50": 54.0,
                "55": 54.0,
                "60": 54.0
            }
        },
        "ids": {
            "-20": {
                "15": 1,
                "20": 2,
                "25": 3,
                "30": 4,
                "35": 5,
                "40": 6,
                "45": 7,
                "50": 8,
                "55": 9,
                "60": 10
            },
            "-15": {
                "15": 11,
                "20": 12,
                "25": 13,
                "30": 14,
                "35": 15,
                "40": 16,
                "45": 17,
                "50": 18,
                "55": 19,
                "60": 20
            },
            "-12": {
                "15": 21,
                "20": 22,
                "25": 23,
                "30": 24,
                "35": 25,
                "40": 26,
                "45": 27,
                "50": 28,
                "55": 29,
                "60": 30
            },
            "-10": {
                "15": 31,
                "20": 32,
                "25": 33,
                "30": 34,
                "35": 35,
                "40": 36,
                "45": 37,
                "50": 38,
                "55": 39,
                "60": 40
            },
            "-7": {
                "15": 41,
                "20": 42,
                "25": 43,
                "30": 44,
                "35": 45,
                "40": 46,
                "45": 47,
                "50": 48,
                "55": 49,
                "60": 50
            },
            "-2": {
                "15": 51,
                "20": 52,
                "25": 53,
                "30": 54,
                "35": 55,
                "40": 56,
                "45": 57,
                "50": 58,
                "55": 59,
                "60": 60
            },
            "2": {
                "15": 61,
                "20": 62,
                "25": 63,
                "30": 64,
                "35": 65,
                "40": 66,
                "45": 67,
                "50": 68,
                "55": 69,
                "60": 70
            },
            "7": {
                "15": 71,
                "20": 72,
                "25": 73,
                "30": 74,
                "35": 75,
                "40": 76,
                "45": 77,
                "50": 78,
                "55": 79,
                "60": 80
            },
            "10": {
                "15": 81,
                "20": 82,
                "25": 83,
                "30": 84,
                "35": 85,
                "40": 86,
                "45": 87,
                "50": 88,
                "55": 89,
                "60": 90
            },
            "12": {
                "15": 91,
                "20": 92,
                "25": 93,
                "30": 94,
                "35": 95,
                "40": 96,
                "45": 97,
                "50": 98,
                "55": 99,
                "60": 100
            },
            "15": {
                "15": 101,
                "20": 102,
                "25": 103,
                "30": 104,
                "35": 105,
                "40": 106,
                "45": 107,
                "50": 108,
                "55": 109,
                "60": 110
            },
            "20": {
                "15": 111,
                "20": 112,
                "25": 113,
                "30": 114,
                "35": 115,
                "40": 116,
                "45": 117,
                "50": 118,
                "55": 119,
                "60": 120
            },
            "25": {
                "15": 121,
                "20": 122,
                "25": 123,
                "30": 124,
                "35": 125,
                "40": 126,
                "45": 127,
                "50": 128,
                "55": 129,
                "60": 130
            },
            "30": {
                "15": 131,
                "20": 132,
                "25": 133,
                "30": 134,
                "35": 135,
                "40": 136,
                "45": 137,
                "50": 138,
                "55": 139,
                "60": 140
            },
            "35": {
                "15": 141,
                "20": 142,
                "25": 143,
                "30": 144,
                "35": 145,
                "40": 146,
                "45": 147,
                "50": 148,
                "55": 149,
                "60": 150
            }
        },
        "min_heatload": 15800,
        "max_heatload": 54000.0
    },
    "Air_30kW_1stage": {
        "eta_s": {
            "-20": {
                "15": 0.56,
                "20": 0.57,
                "25": 0.58,
                "30": 0.57,
                "35": 0.29,
                "40": 0.39,
                "45": 0.29,
                "50": null,
                "55": null,
                "60": null
            },
            "-15": {
                "15": 0.57,
                "20": 0.59,
                "25": 0.6,
                "30": 0.61,
                "35": 0.48,
                "40": 0.51,
                "45": 0.46,
                "50": null,
                "55": null,
                "60": null
            },
            "-12": {
                "15": 0.57,
                "20": 0.59,
                "25": 0.61,
                "30": 0.62,
                "35": 0.57,
                "40": 0.58,
                "45": 0.53,
                "50": null,
                "55": null,
                "60": null
            },
            "-10": {
                "15": 0.56,
                "20": 0.59,
                "25": 0.61,
                "30": 0.62,
                "35": 0.57,
                "40": 0.59,
                "45": 0.57,
                "50": 0.49,
                "55": null,
                "60": null
            },
            "-7": {
                "15": 0.56,
                "20": 0.59,
                "25": 0.61,
                "30": 0.63,
                "35": 0.6,
                "40": 0.63,
                "45": 0.62,
                "50": 0.57,
                "55": 0.62,
                "60": null
            },
            "-2": {
                "15": 0.54,
                "20": 0.57,
                "25": 0.6,
                "30": 0.63,
                "35": 0.62,
                "40": 0.67,
                "45": 0.68,
                "50": 0.67,
                "55": 0.69,
                "60": 0.54
            },
            "2": {
                "15": 0.54,
                "20": 0.55,
                "25": 0.59,
                "30": 0.62,
                "35": 0.64,
                "40": 0.68,
                "45": 0.7,
                "50": 0.71,
                "55": 0.74,
                "60": 0.68
            },
            "7": {
                "15": 0.52,
                "20": 0.53,
                "25": 0.56,
                "30": 0.61,
                "35": 0.65,
                "40": 0.69,
                "45": 0.72,
                "50": 0.74,
                "55": 0.85,
                "60": 0.8
            },
            "10": {
                "15": 0.54,
                "20": 0.53,
                "25": 0.54,
                "30": 0.59,
                "35": 0.7,
                "40": 0.69,
                "45": 0.72,
                "50": 0.76,
                "55": 0.88,
                "60": 0.85
            },
            "12": {
                "15": 0.6,
                "20": 0.53,
                "25": 0.54,
                "30": 0.58,
                "35": 0.7,
                "40": 0.69,
                "45": 0.72,
                "50": 0.76,
                "55": 0.89,
                "60": 0.88
            },
            "15": {
                "15": null,
                "20": 0.54,
                "25": 0.53,
                "30": 0.56,
                "35": 0.68,
                "40": 0.67,
                "45": 0.71,
                "50": 0.77,
                "55": 0.88,
                "60": 0.89
            },
            "20": {
                "15": null,
                "20": null,
                "25": 0.55,
                "30": 0.54,
                "35": 0.61,
                "40": 0.63,
                "45": 0.69,
                "50": 0.75,
                "55": 0.85,
                "60": 0.92
            },
            "25": {
                "15": null,
                "20": null,
                "25": null,
                "30": 0.56,
                "35": 0.55,
                "40": 0.59,
                "45": 0.66,
                "50": 0.73,
                "55": 0.8,
                "60": 0.92
            },
            "30": {
                "15": null,
                "20": null,
                "25": null,
                "30": null,
                "35": 0.45,
                "40": 0.56,
                "45": 0.62,
                "50": 0.69,
                "55": 0.73,
                "60": 0.9
            },
            "35": {
                "15": null,
                "20": null,
                "25": null,
                "30": null,
                "35": null,
                "40": 0.58,
                "45": 0.59,
                "50": 0.65,
                "55": 0.66,
                "60": 0.86
            }
        },
        "heatload": {
            "-20": {
                "15": 7.3,
                "20": 7.3,
                "25": 7.3,
                "30": 7.3,
                "35": 7.3,
                "40": 7.3,
                "45": 7.3,
                "50": null,
                "55": null,
                "60": null
            },
            "-15": {
                "15": 9.5,
                "20": 9.5,
                "25": 9.5,
                "30": 9.5,
                "35": 9.5,
                "40": 9.5,
                "45": 9.5,
                "50": null,
                "55": null,
                "60": null
            },
            "-12": {
                "15": 11.0,
                "20": 11.0,
                "25": 11.0,
                "30": 11.0,
                "35": 11.0,
                "40": 11.0,
                "45": 11.0,
                "50": null,
                "55": null,
                "60": null
            },
            "-10": {
                "15": 12.0,
                "20": 12.0,
                "25": 12.0,
                "30": 12.0,
                "35": 12.0,
                "40": 12.0,
                "45": 12.0,
                "50": 12.0,
                "55": null,
                "60": null
            },
            "-7": {
                "15": 13.13,
                "20": 13.13,
                "25": 13.13,
                "30": 13.13,
                "35": 13.45,
                "40": 13.13,
                "45": 13.13,
                "50": 13.13,
                "55": 12.8,
                "60": null
            },
            "-2": {
                "15": 14.75,
                "20": 14.75,
                "25": 14.75,
                "30": 14.75,
                "35": 15.3,
                "40": 14.75,
                "45": 14.75,
                "50": 14.75,
                "55": 14.2,
                "60": 14.75
            },
            "2": {
                "15": 16.34,
                "20": 16.34,
                "25": 16.34,
                "30": 16.34,
                "35": 16.97,
                "40": 16.34,
                "45": 16.34,
                "50": 16.34,
                "55": 15.7,
                "60": 16.34
            },
            "7": {
                "15": 19.39,
                "20": 19.39,
                "25": 19.39,
                "30": 19.39,
                "35": 19.78,
                "40": 19.39,
                "45": 19.39,
                "50": 19.39,
                "55": 19.0,
                "60": 19.39
            },
            "10": {
                "15": 21.5,
                "20": 21.5,
                "25": 21.5,
                "30": 21.5,
                "35": 22.0,
                "40": 21.5,
                "45": 21.5,
                "50": 21.5,
                "55": 21.0,
                "60": 21.5
            },
            "12": {
                "15": 22.6,
                "20": 22.6,
                "25": 22.6,
                "30": 22.6,
                "35": 23.1,
                "40": 22.6,
                "45": 22.6,
                "50": 22.6,
                "55": 22.1,
                "60": 22.6
            },
            "15": {
                "15": null,
                "20": 23.75,
                "25": 23.75,
                "30": 23.75,
                "35": 24.3,
                "40": 23.75,
                "45": 23.75,
                "50": 23.75,
                "55": 23.2,
                "60": 23.75
            },
            "20": {
                "15": null,
                "20": null,
                "25": 25.5,
                "30": 25.5,
                "35": 26.0,
                "40": 25.5,
                "45": 25.5,
                "50": 25.5,
                "55": 25.0,
                "60": 25.5
            },
            "25": {
                "15": null,
                "20": null,
                "25": null,
                "30": 27.4,
                "35": 28.0,
                "40": 27.4,
                "45": 27.4,
                "50": 27.4,
                "55": 26.8,
                "60": 27.4
            },
            "30": {
                "15": null,
                "20": null,
                "25": null,
                "30": null,
                "35": 29.9,
                "40": 29.15,
                "45": 29.15,
                "50": 29.15,
                "55": 28.4,
                "60": 29.15
            },
            "35": {
                "15": null,
                "20": null,
                "25": null,
                "30": null,
                "35": null,
                "40": 30.95,
                "45": 30.95,
                "50": 30.95,
                "55": 30.0,
                "60": 30.95
            }
        },
        "ids": {
            "-20": {
                "15": 1,
                "20": 2,
                "25": 3,
                "30": 4,
                "35": 5,
                "40": 6,
                "45": 7,
                "50": 8,
                "55": 9,
                "60": 10
            },
            "-15": {
                "15": 11,
                "20": 12,
                "25": 13,
                "30": 14,
                "35": 15,
                "40": 16,
                "45": 17,
                "50": 18,
                "55": 19,
                "60": 20
            },
            "-12": {
                "15": 21,
                "20": 22,
                "25": 23,
                "30": 24,
                "35": 25,
                "40": 26,
                "45": 27,
                "50": 28,
                "55": 29,
                "60": 30
            },
            "-10": {
                "15": 31,
                "20": 32,
                "25": 33,
                "30": 34,
                "35": 35,
                "40": 36,
                "45": 37,
                "50": 38,
                "55": 39,
                "60": 40
            },
            "-7": {
                "15": 41,
                "20": 42,
                "25": 43,
                "30": 44,
                "35": 45,
                "40": 46,
                "45": 47,
                "50": 48,
                "55": 49,
                "60": 50
            },
            "-2": {
                "15": 51,
                "20": 52,
                "25": 53,
                "30": 54,
                "35": 55,
                "40": 56,
                "45": 57,
                "50": 58,
                "55": 59,
                "60": 60
            },
            "2": {
                "15": 61,
                "20": 62,
                "25": 63,
                "30": 64,
                "35": 65,
                "40": 66,
                "45": 67,
                "50": 68,
                "55": 69,
                "60": 70
            },
            "7": {
                "15": 71,
                "20": 72,
                "25": 73,
                "30": 74,
                "35": 75,
                "40": 76,
                "45": 77,
                "50": 78,
                "55": 79,
                "60": 80
            },
            "10": {
                "15": 81,
                "20": 82,
                "25": 83,
                "30": 84,
                "35": 85,
                "40": 86,
                "45": 87,
                "50": 88,
                "55": 89,
                "60": 90
            },
            "12": {
                "15": 91,
                "20": 92,
                "25": 93,
                "30": 94,
                "35": 95,
                "40": 96,
                "45": 97,
                "50": 98,
                "55": 99,
                "60": 100
            },
            "15": {
                "15": 101,
                "20": 102,
                "25": 103,
                "30": 104,
                "35": 105,
                "40": 106,
                "45": 107,
                "50": 108,
                "55": 109,
                "60": 110
            },
            "20": {
                "15": 111,
                "20": 112,
                "25": 113,
                "30": 114,
                "35": 115,
                "40": 116,
                "45": 117,
                "50": 118,
                "55": 119,
                "60": 120
            },
            "25": {
                "15": 121,
                "20": 122,
                "25": 123,
                "30": 124,
                "35": 125,
                "40": 126,
                "45": 127,
                "50": 128,
                "55": 129,
                "60": 130
            },
            "30": {
                "15": 131,
                "20": 132,
                "25": 133,
                "30": 134,
                "35": 135,
                "40": 136,
                "45": 137,
                "50": 138,
                "55": 139,
                "60": 140
            },
            "35": {
                "15": 141,
                "20": 142,
                "25": 143,
                "30": 144,
                "35": 145,
                "40": 146,
                "45": 147,
                "50": 148,
                "55": 149,
                "60": 150
            }
        },
        "min_heatload": 7300.0,
        "max_heatload": 30950.0
    },
    "Air_6kW": {
        "eta_s": {
            "-20": {
                "15": 0.59,
                "20": 0.58,
                "25": 0.57,
                "30": 0.3,
                "35": 0.3,
                "40": 0.3,
                "45": 0.3,
                "50": 0.3,
                "55": null
            },
            "-15": {
                "15": 0.59,
                "20": 0.58,
                "25": 0.57,
                "30": 0.47,
                "35": 0.41,
                "40": 0.32,
                "45": 0.3,
                "50": 0.3,
                "55": 0.3
            },
            "-12": {
                "15": 0.59,
                "20": 0.58,
                "25": 0.57,
                "30": 0.56,
                "35": 0.55,
                "40": 0.52,
                "45": 0.43,
                "50": 0.31,
                "55": 0.3
            },
            "-10": {
                "15": 0.59,
                "20": 0.59,
                "25": 0.58,
                "30": 0.57,
                "35": 0.56,
                "40": 0.55,
                "45": 0.47,
                "50": 0.37,
                "55": 0.3
            },
            "-7": {
                "15": 0.59,
                "20": 0.6,
                "25": 0.6,
                "30": 0.59,
                "35": 0.57,
                "40": 0.55,
                "45": 0.54,
                "50": 0.53,
                "55": 0.52
            },
            "-2": {
                "15": 0.61,
                "20": 0.61,
                "25": 0.61,
                "30": 0.6,
                "35": 0.59,
                "40": 0.58,
                "45": 0.57,
                "50": 0.58,
                "55": 0.57
            },
            "2": {
                "15": 0.61,
                "20": 0.62,
                "25": 0.62,
                "30": 0.61,
                "35": 0.6,
                "40": 0.59,
                "45": 0.59,
                "50": 0.6,
                "55": 0.59
            },
            "7": {
                "15": 0.63,
                "20": 0.63,
                "25": 0.62,
                "30": 0.63,
                "35": 0.64,
                "40": 0.65,
                "45": 0.66,
                "50": 0.69,
                "55": 0.7
            },
            "10": {
                "15": 0.74,
                "20": 0.73,
                "25": 0.7,
                "30": 0.69,
                "35": 0.68,
                "40": 0.67,
                "45": 0.66,
                "50": 0.66,
                "55": 0.66
            },
            "12": {
                "15": 0.92,
                "20": 0.81,
                "25": 0.72,
                "30": 0.66,
                "35": 0.65,
                "40": 0.66,
                "45": 0.67,
                "50": 0.68,
                "55": 0.69
            },
            "15": {
                "15": null,
                "20": 0.75,
                "25": 0.74,
                "30": 0.67,
                "35": 0.67,
                "40": 0.68,
                "45": 0.69,
                "50": 0.7,
                "55": 0.71
            },
            "20": {
                "15": null,
                "20": null,
                "25": 0.77,
                "30": 0.64,
                "35": 0.65,
                "40": 0.66,
                "45": 0.68,
                "50": 0.72,
                "55": 0.75
            },
            "25": {
                "15": null,
                "20": null,
                "25": null,
                "30": 0.78,
                "35": 0.77,
                "40": 0.74,
                "45": 0.73,
                "50": 0.72,
                "55": 0.73
            }
        },
        "heatload": {
            "-20": {
                "15": 3.56,
                "20": 3.44,
                "25": 3.31,
                "30": 3.16,
                "35": 3.11,
                "40": 2.93,
                "45": 2.75,
                "50": 2.71,
                "55": null
            },
            "-15": {
                "15": 4.65,
                "20": 4.48,
                "25": 4.31,
                "30": 4.13,
                "35": 4.01,
                "40": 3.77,
                "45": 3.6,
                "50": 3.54,
                "55": 3.26
            },
            "-12": {
                "15": 5.05,
                "20": 4.88,
                "25": 4.71,
                "30": 4.48,
                "35": 4.39,
                "40": 4.25,
                "45": 4.08,
                "50": 3.99,
                "55": 3.59
            },
            "-10": {
                "15": 5.5,
                "20": 5.32,
                "25": 5.14,
                "30": 4.89,
                "35": 4.79,
                "40": 4.63,
                "45": 4.45,
                "50": 4.34,
                "55": 3.93
            },
            "-7": {
                "15": 6.03,
                "20": 5.87,
                "25": 5.71,
                "30": 5.48,
                "35": 5.34,
                "40": 5.29,
                "45": 5.21,
                "50": 4.99,
                "55": 4.58
            },
            "-2": {
                "15": 6.86,
                "20": 6.67,
                "25": 6.47,
                "30": 6.15,
                "35": 6.08,
                "40": 6.04,
                "45": 5.69,
                "50": 5.58,
                "55": 5.14
            },
            "2": {
                "15": 7.19,
                "20": 7.0,
                "25": 6.8,
                "30": 6.58,
                "35": 6.4,
                "40": 6.19,
                "45": 6.07,
                "50": 5.97,
                "55": 5.49
            },
            "7": {
                "15": 9.45,
                "20": 9.17,
                "25": 8.89,
                "30": 8.48,
                "35": 8.35,
                "40": 8.17,
                "45": 7.95,
                "50": 7.53,
                "55": 7.08
            },
            "10": {
                "15": 10.0,
                "20": 9.69,
                "25": 9.37,
                "30": 8.95,
                "35": 8.74,
                "40": 8.5,
                "45": 8.2,
                "50": 7.83,
                "55": 7.34
            },
            "12": {
                "15": 10.3,
                "20": 9.96,
                "25": 9.63,
                "30": 9.2,
                "35": 8.97,
                "40": 8.73,
                "45": 8.37,
                "50": 8.01,
                "55": 7.52
            },
            "15": {
                "15": null,
                "20": 10.88,
                "25": 10.51,
                "30": 10.03,
                "35": 9.77,
                "40": 9.46,
                "45": 9.1,
                "50": 8.65,
                "55": 8.14
            },
            "20": {
                "15": null,
                "20": null,
                "25": 12.07,
                "30": 11.51,
                "35": 11.21,
                "40": 10.85,
                "45": 10.44,
                "50": 9.89,
                "55": 9.31
            },
            "25": {
                "15": null,
                "20": null,
                "25": null,
                "30": 12.0,
                "35": 11.71,
                "40": 11.4,
                "45": 11.01,
                "50": 10.45,
                "55": 9.9
            }
        },
        "ids": {
            "-20": {
                "15": 1,
                "20": 2,
                "25": 3,
                "30": 4,
                "35": 5,
                "40": 6,
                "45": 7,
                "50": 8,
                "55": 9
            },
            "-15": {
                "15": 10,
                "20": 11,
                "25": 12,
                "30": 13,
                "35": 14,
                "40": 15,
                "45": 16,
                "50": 17,
                "55": 18
            },
            "-12": {
                "15": 19,
                "20": 20,
                "25": 21,
                "30": 22,
                "35": 23,
                "40": 24,
                "45": 25,
                "50": 26,
                "55": 27
            },
            "-10": {
                "15": 28,
                "20": 29,
                "25": 30,
                "30": 31,
                "35": 32,
                "40": 33,
                "45": 34,
                "50": 35,
                "55": 36
            },
            "-7": {
                "15": 37,
                "20": 38,
                "25": 39,
                "30": 40,
                "35": 41,
                "40": 42,
                "45": 43,
                "50": 44,
                "55": 45
            },
            "-2": {
                "15": 46,
                "20": 47,
                "25": 48,
                "30": 49,
                "35": 50,
                "40": 51,
                "45": 52,
                "50": 53,
                "55": 54
            },
            "2": {
                "15": 55,
                "20": 56,
                "25": 57,
                "30": 58,
                "35": 59,
                "40": 60,
                "45": 61,
                "50": 62,
                "55": 63
            },
            "7": {
                "15": 64,
                "20": 65,
                "25": 66,
                "30": 67,
                "35": 68,
                "40": 69,
                "45": 70,
                "50": 71,
                "55": 72
            },
            "10": {
                "15": 73,
                "20": 74,
                "25": 75,
                "30": 76,
                "35": 77,
                "40": 78,
                "45": 79,
                "50": 80,
                "55": 81
            },
            "12": {
                "15": 82,
                "20": 83,
                "25": 84,
                "30": 85,
                "35": 86,
                "40": 87,
                "45": 88,
                "50": 89,
                "55": 90
            },
            "15": {
                "15": 91,
                "20": 92,
                "25": 93,
                "30": 94,
                "35": 95,
                "40": 96,
                "45": 97,
                "50": 98,
                "55": 99
            },
            "20": {
                "15": 100,
                "20": 101,
                "25": 102,
                "30": 103,
                "35": 104,
                "40": 105,
                "45": 106,
                "50": 107,
                "55": 108
            },
            "25": {
                "15": 109,
                "20": 110,
                "25": 111,
                "30": 112,
                "35": 113,
                "40": 114,
                "45": 115,
                "50": 116,
                "55": 117
            }
        },
        "min_heatload": 1800,
        "max_heatload": 12070.0
    },
    "Air_8kW": {
        "eta_s": {
            "-20": {
                "15": 0.59,
                "20": 0.56,
                "25": 0.52,
                "30": 0.3,
                "35": 0.3,
                "40": 0.3,
                "45": 0.3,
                "50": 0.3,
                "55": null
            },
            "-15": {
                "15": 0.59,
                "20": 0.58,
                "25": 0.56,
                "30": 0.4,
                "35": 0.35,
                "40": 0.3,
                "45": 0.3,
                "50": 0.3,
                "55": 0.3
            },
            "-12": {
                "15": 0.59,
                "20": 0.58,
                "25": 0.57,
                "30": 0.55,
                "35": 0.51,
                "40": 0.44,
                "45": 0.36,
                "50": 0.3,
                "55": 0.3
            },
            "-10": {
                "15": 0.59,
                "20": 0.58,
                "25": 0.57,
                "30": 0.56,
                "35": 0.53,
                "40": 0.48,
                "45": 0.4,
                "50": 0.31,
                "55": 0.3
            },
            "-7": {
                "15": 0.59,
                "20": 0.58,
                "25": 0.57,
                "30": 0.55,
                "35": 0.51,
                "40": 0.48,
                "45": 0.47,
                "50": 0.46,
                "55": 0.44
            },
            "-2": {
                "15": 0.59,
                "20": 0.58,
                "25": 0.57,
                "30": 0.56,
                "35": 0.55,
                "40": 0.54,
                "45": 0.53,
                "50": 0.53,
                "55": 0.52
            },
            "2": {
                "15": 0.59,
                "20": 0.58,
                "25": 0.57,
                "30": 0.56,
                "35": 0.55,
                "40": 0.54,
                "45": 0.54,
                "50": 0.55,
                "55": 0.54
            },
            "7": {
                "15": 0.61,
                "20": 0.6,
                "25": 0.59,
                "30": 0.6,
                "35": 0.61,
                "40": 0.62,
                "45": 0.63,
                "50": 0.64,
                "55": 0.65
            },
            "10": {
                "15": 0.71,
                "20": 0.68,
                "25": 0.63,
                "30": 0.62,
                "35": 0.61,
                "40": 0.6,
                "45": 0.6,
                "50": 0.6,
                "55": 0.59
            },
            "12": {
                "15": 0.9,
                "20": 0.73,
                "25": 0.65,
                "30": 0.6,
                "35": 0.6,
                "40": 0.61,
                "45": 0.62,
                "50": 0.63,
                "55": 0.64
            },
            "15": {
                "15": null,
                "20": 0.72,
                "25": 0.68,
                "30": 0.6,
                "35": 0.61,
                "40": 0.62,
                "45": 0.63,
                "50": 0.64,
                "55": 0.66
            },
            "20": {
                "15": null,
                "20": null,
                "25": 0.75,
                "30": 0.58,
                "35": 0.59,
                "40": 0.62,
                "45": 0.64,
                "50": 0.67,
                "55": 0.7
            },
            "25": {
                "15": null,
                "20": null,
                "25": null,
                "30": 0.75,
                "35": 0.71,
                "40": 0.67,
                "45": 0.66,
                "50": 0.67,
                "55": 0.68
            }
        },
        "heatload": {
            "-20": {
                "15": 4.27,
                "20": 4.12,
                "25": 3.97,
                "30": 3.79,
                "35": 3.73,
                "40": 3.51,
                "45": 3.29,
                "50": 3.25,
                "55": null
            },
            "-15": {
                "15": 5.58,
                "20": 5.38,
                "25": 5.17,
                "30": 4.96,
                "35": 4.81,
                "40": 4.52,
                "45": 4.33,
                "50": 4.24,
                "55": 3.92
            },
            "-12": {
                "15": 6.05,
                "20": 5.85,
                "25": 5.65,
                "30": 5.38,
                "35": 5.27,
                "40": 5.09,
                "45": 4.89,
                "50": 4.79,
                "55": 4.31
            },
            "-10": {
                "15": 6.59,
                "20": 6.38,
                "25": 6.16,
                "30": 5.87,
                "35": 5.74,
                "40": 5.56,
                "45": 5.34,
                "50": 5.21,
                "55": 4.72
            },
            "-7": {
                "15": 7.23,
                "20": 7.04,
                "25": 6.85,
                "30": 6.57,
                "35": 6.41,
                "40": 6.35,
                "45": 6.25,
                "50": 5.99,
                "55": 5.5
            },
            "-2": {
                "15": 8.24,
                "20": 8.0,
                "25": 7.76,
                "30": 7.38,
                "35": 7.29,
                "40": 7.25,
                "45": 6.82,
                "50": 6.7,
                "55": 6.16
            },
            "2": {
                "15": 8.64,
                "20": 8.4,
                "25": 8.17,
                "30": 7.9,
                "35": 7.68,
                "40": 7.43,
                "45": 7.28,
                "50": 7.16,
                "55": 6.59
            },
            "7": {
                "15": 11.33,
                "20": 11.0,
                "25": 10.67,
                "30": 10.17,
                "35": 10.02,
                "40": 9.81,
                "45": 9.53,
                "50": 9.04,
                "55": 8.5
            },
            "10": {
                "15": 12.0,
                "20": 11.62,
                "25": 11.24,
                "30": 10.74,
                "35": 10.49,
                "40": 10.2,
                "45": 9.83,
                "50": 9.4,
                "55": 8.81
            },
            "12": {
                "15": 12.35,
                "20": 11.95,
                "25": 11.55,
                "30": 11.04,
                "35": 10.76,
                "40": 10.48,
                "45": 10.05,
                "50": 9.61,
                "55": 9.03
            },
            "15": {
                "15": null,
                "20": 13.07,
                "25": 12.61,
                "30": 12.04,
                "35": 11.72,
                "40": 11.35,
                "45": 10.92,
                "50": 10.38,
                "55": 9.76
            },
            "20": {
                "15": null,
                "20": null,
                "25": 14.49,
                "30": 13.81,
                "35": 13.46,
                "40": 13.01,
                "45": 12.52,
                "50": 11.87,
                "55": 11.17
            },
            "25": {
                "15": null,
                "20": null,
                "25": null,
                "30": 14.4,
                "35": 14.05,
                "40": 13.68,
                "45": 13.2,
                "50": 12.54,
                "55": 11.87
            }
        },
        "ids": {
            "-20": {
                "15": 1,
                "20": 2,
                "25": 3,
                "30": 4,
                "35": 5,
                "40": 6,
                "45": 7,
                "50": 8,
                "55": 9
            },
            "-15": {
                "15": 10,
                "20": 11,
                "25": 12,
                "30": 13,
                "35": 14,
                "40": 15,
                "45": 16,
                "50": 17,
                "55": 18
            },
            "-12": {
                "15": 19,
                "20": 20,
                "25": 21,
                "30": 22,
                "35": 23,
                "40": 24,
                "45": 25,
                "50": 26,
                "55": 27
            },
            "-10": {
                "15": 28,
                "20": 29,
                "25": 30,
                "30": 31,
                "35": 32,
                "40": 33,
                "45": 34,
                "50": 35,
                "55": 36
            },
            "-7": {
                "15": 37,
                "20": 38,
                "25": 39,
                "30": 40,
                "35": 41,
                "40": 42,
                "45": 43,
                "50": 44,
                "55": 45
            },
            "-2": {
                "15": 46,
                "20": 47,
                "25": 48,
                "30": 49,
                "35": 50,
                "40": 51,
                "45": 52,
                "50": 53,
                "55": 54
            },
            "2": {
                "15": 55,
                "20": 56,
                "25": 57,
                "30": 58,
                "35": 59,
                "40": 60,
                "45": 61,
                "50": 62,
                "55": 63
            },
            "7": {
                "15": 64,
                "20": 65,
                "25": 66,
                "30": 67,
                "35": 68,
                "40": 69,
                "45": 70,
                "50": 71,
                "55": 72
            },
            "10": {
                "15": 73,
                "20": 74,
                "25": 75,
                "30": 76,
                "35": 77,
                "40": 78,
                "45": 79,
                "50": 80,
                "55": 81
            },
            "12": {
                "15": 82,
                "20": 83,
                "25": 84,
                "30": 85,
                "35": 86,
                "40": 87,
                "45": 88,
                "50": 89,
                "55": 90
            },
            "15": {
                "15": 91,
                "20": 92,
                "25": 93,
                "30": 94,
                "35": 95,
                "40": 96,
                "45": 97,
                "50": 98,
                "55": 99
            },
            "20": {
                "15": 100,
                "20": 101,
                "25": 102,
                "30": 103,
                "35": 104,
                "40": 105,
                "45": 106,
                "50": 107,
                "55": 108
            },
            "25": {
                "15": 109,
                "20": 110,
                "25": 111,
                "30": 112,
                "35": 113,
                "40": 114,
                "45": 115,
                "50": 116,
                "55": 117
            }
        },
        "min_heatload": 1800,
        "max_heatload": 14490.0
    },
    "Air_16kW": {
        "eta_s": {
            "-20": {
                "15": 0.47,
                "20": 0.44,
                "25": 0.4,
                "30": 0.3,
                "35": 0.3,
                "40": 0.3,
                "45": 0.3,
                "50": null,
                "55": null
            },
            "-15": {
                "15": 0.51,
                "20": 0.48,
                "25": 0.45,
                "30": 0.3,
                "35": 0.3,
                "40": 0.3,
                "45": 0.3,
                "50": 0.3,
                "55": null
            },
            "-12": {
                "15": 0.52,
                "20": 0.5,
                "25": 0.48,
                "30": 0.45,
                "35": 0.4,
                "40": 0.35,
                "45": 0.3,
                "50": 0.3,
                "55": 0.3
            },
            "-10": {
                "15": 0.54,
                "20": 0.51,
                "25": 0.49,
                "30": 0.46,
                "35": 0.43,
                "40": 0.38,
                "45": 0.32,
                "50": 0.3,
                "55": 0.3
            },
            "-7": {
                "15": 0.56,
                "20": 0.53,
                "25": 0.51,
                "30": 0.42,
                "35": 0.4,
                "40": 0.38,
                "45": 0.33,
                "50": 0.3,
                "55": 0.3
            },
            "-2": {
                "15": 0.59,
                "20": 0.57,
                "25": 0.55,
                "30": 0.44,
                "35": 0.43,
                "40": 0.4,
                "45": 0.39,
                "50": 0.34,
                "55": 0.31
            },
            "2": {
                "15": 0.61,
                "20": 0.6,
                "25": 0.58,
                "30": 0.46,
                "35": 0.45,
                "40": 0.43,
                "45": 0.44,
                "50": 0.4,
                "55": 0.35
            },
            "7": {
                "15": 0.72,
                "20": 0.67,
                "25": 0.61,
                "30": 0.64,
                "35": 0.66,
                "40": 0.66,
                "45": 0.65,
                "50": 0.64,
                "55": 0.6
            },
            "10": {
                "15": 0.91,
                "20": 0.74,
                "25": 0.64,
                "30": 0.6,
                "35": 0.58,
                "40": 0.57,
                "45": 0.55,
                "50": 0.54,
                "55": 0.52
            },
            "12": {
                "15": 0.95,
                "20": 0.83,
                "25": 0.68,
                "30": 0.62,
                "35": 0.62,
                "40": 0.62,
                "45": 0.62,
                "50": 0.61,
                "55": 0.58
            },
            "15": {
                "15": null,
                "20": 0.93,
                "25": 0.75,
                "30": 0.61,
                "35": 0.62,
                "40": 0.63,
                "45": 0.63,
                "50": 0.62,
                "55": 0.61
            },
            "20": {
                "15": null,
                "20": null,
                "25": 0.95,
                "30": 0.58,
                "35": 0.59,
                "40": 0.61,
                "45": 0.64,
                "50": 0.65,
                "55": 0.64
            },
            "25": {
                "15": null,
                "20": null,
                "25": null,
                "30": 0.95,
                "35": 0.78,
                "40": 0.69,
                "45": 0.66,
                "50": 0.65,
                "55": 0.65
            },
            "30": {
                "15": null,
                "20": null,
                "25": null,
                "30": null,
                "35": 0.82,
                "40": 0.55,
                "45": 0.42,
                "50": 0.35,
                "55": 0.32
            },
            "35": {
                "15": null,
                "20": null,
                "25": null,
                "30": null,
                "35": null,
                "40": 0.85,
                "45": 0.57,
                "50": 0.44,
                "55": 0.38
            }
        },
        "heatload": {
            "-20": {
                "15": 11.68,
                "20": 11.11,
                "25": 10.55,
                "30": 9.56,
                "35": 9.66,
                "40": 9.59,
                "45": 7.69,
                "50": null,
                "55": null
            },
            "-15": {
                "15": 12.15,
                "20": 11.69,
                "25": 11.24,
                "30": 10.57,
                "35": 10.56,
                "40": 9.86,
                "45": 9.55,
                "50": 8.79,
                "55": null
            },
            "-12": {
                "15": 13.83,
                "20": 13.02,
                "25": 12.21,
                "30": 10.73,
                "35": 10.63,
                "40": 10.3,
                "45": 9.55,
                "50": 8.54,
                "55": 6.46
            },
            "-10": {
                "15": 14.27,
                "20": 13.49,
                "25": 12.7,
                "30": 11.3,
                "35": 11.16,
                "40": 10.81,
                "45": 10.1,
                "50": 9.12,
                "55": 7.16
            },
            "-7": {
                "15": 15.03,
                "20": 14.35,
                "25": 13.67,
                "30": 12.59,
                "35": 12.3,
                "40": 12.02,
                "45": 11.35,
                "50": 10.26,
                "55": 9.18
            },
            "-2": {
                "15": 13.93,
                "20": 13.41,
                "25": 12.9,
                "30": 12.11,
                "35": 11.79,
                "40": 11.48,
                "45": 11.39,
                "50": 10.44,
                "55": 9.32
            },
            "2": {
                "15": 12.41,
                "20": 12.18,
                "25": 11.95,
                "30": 11.74,
                "35": 11.4,
                "40": 11.07,
                "45": 11.37,
                "50": 11.04,
                "55": 10.29
            },
            "7": {
                "15": 18.23,
                "20": 17.7,
                "25": 17.17,
                "30": 16.63,
                "35": 16.1,
                "40": 15.47,
                "45": 15.22,
                "50": 14.51,
                "55": 13.92
            },
            "10": {
                "15": 18.69,
                "20": 18.14,
                "25": 17.59,
                "30": 17.01,
                "35": 16.46,
                "40": 15.88,
                "45": 15.61,
                "50": 14.92,
                "55": 14.15
            },
            "12": {
                "15": 18.98,
                "20": 18.42,
                "25": 17.87,
                "30": 17.34,
                "35": 16.74,
                "40": 16.13,
                "45": 15.76,
                "50": 15.13,
                "55": 14.51
            },
            "15": {
                "15": null,
                "20": 19.98,
                "25": 19.38,
                "30": 18.81,
                "35": 18.16,
                "40": 17.51,
                "45": 17.1,
                "50": 16.43,
                "55": 15.75
            },
            "20": {
                "15": null,
                "20": null,
                "25": 22.14,
                "30": 21.49,
                "35": 20.77,
                "40": 20.04,
                "45": 19.59,
                "50": 18.83,
                "55": 18.07
            },
            "25": {
                "15": null,
                "20": null,
                "25": null,
                "30": 21.29,
                "35": 20.43,
                "40": 19.69,
                "45": 19.74,
                "50": 19.27,
                "55": 19.4
            },
            "30": {
                "15": null,
                "20": null,
                "25": null,
                "30": null,
                "35": 21.75,
                "40": 20.96,
                "45": 21.12,
                "50": 20.72,
                "55": 21.15
            },
            "35": {
                "15": null,
                "20": null,
                "25": null,
                "30": null,
                "35": null,
                "40": 22.23,
                "45": 22.5,
                "50": 22.17,
                "55": 22.9
            }
        },
        "ids": {
            "-20": {
                "15": 1,
                "20": 2,
                "25": 3,
                "30": 4,
                "35": 5,
                "40": 6,
                "45": 7,
                "50": 8,
                "55": 9
            },
            "-15": {
                "15": 10,
                "20": 11,
                "25": 12,
                "30": 13,
                "35": 14,
                "40": 15,
                "45": 16,
                "50": 17,
                "55": 18
            },
            "-12": {
                "15": 19,
                "20": 20,
                "25": 21,
                "30": 22,
                "35": 23,
                "40": 24,
                "45": 25,
                "50": 26,
                "55": 27
            },
            "-10": {
                "15": 28,
                "20": 29,
                "25": 30,
                "30": 31,
                "35": 32,
                "40": 33,
                "45": 34,
                "50": 35,
                "55": 36
            },
            "-7": {
                "15": 37,
                "20": 38,
                "25": 39,
                "30": 40,
                "35": 41,
                "40": 42,
                "45": 43,
                "50": 44,
                "55": 45
            },
            "-2": {
                "15": 46,
                "20": 47,
                "25": 48,
                "30": 49,
                "35": 50,
                "40": 51,
                "45": 52,
                "50": 53,
                "55": 54
            },
            "2": {
                "15": 55,
                "20": 56,
                "25": 57,
                "30": 58,
                "35": 59,
                "40": 60,
                "45": 61,
                "50": 62,
                "55": 63
            },
            "7": {
                "15": 64,
                "20": 65,
                "25": 66,
                "30": 67,
                "35": 68,
                "40": 69,
                "45": 70,
                "50": 71,
                "55": 72
            },
            "10": {
                "15": 73,
                "20": 74,
                "25": 75,
                "30": 76,
                "35": 77,
                "40": 78,
                "45": 79,
                "50": 80,
                "55": 81
            },
            "12": {
                "15": 82,
                "20": 83,
                "25": 84,
                "30": 85,
                "35": 86,
                "40": 87,
                "45": 88,
                "50": 89,
                "55": 90
            },
            "15": {
                "15": 91,
                "20": 92,
                "25": 93,
                "30": 94,
                "35": 95,
                "40": 96,
                "45": 97,
                "50": 98,
                "55": 99
            },
            "20": {
                "15": 100,
                "20": 101,
                "25": 102,
                "30": 103,
                "35": 104,
                "40": 105,
                "45": 106,
                "50": 107,
                "55": 108
            },
            "25": {
                "15": 109,
                "20": 110,
                "25": 111,
                "30": 112,
                "35": 113,
                "40": 114,
                "45": 115,
                "50": 116,
                "55": 117
            },
            "30": {
                "15": 118,
                "20": 119,
                "25": 120,
                "30": 121,
                "35": 122,
                "40": 123,
                "45": 124,
                "50": 125,
                "55": 126
            },
            "35": {
                "15": 127,
                "20": 128,
                "25": 129,
                "30": 130,
                "35": 131,
                "40": 132,
                "45": 133,
                "50": 134,
                "55": 135
            }
        },
        "min_heatload": 6460.0,
        "max_heatload": 22900.0
    },
    "Air_60kW_1stage": {
        "eta_s": {
            "-20": {
                "15": 0.57,
                "20": 0.56,
                "25": 0.55,
                "30": 0.52,
                "35": 0.47,
                "40": 0.41,
                "45": 0.36,
                "50": 0.3,
                "55": null,
                "60": null,
                "65": null
            },
            "-15": {
                "15": 0.56,
                "20": 0.57,
                "25": 0.57,
                "30": 0.55,
                "35": 0.53,
                "40": 0.48,
                "45": 0.44,
                "50": 0.34,
                "55": 0.32,
                "60": null,
                "65": null
            },
            "-12": {
                "15": 0.56,
                "20": 0.57,
                "25": 0.57,
                "30": 0.57,
                "35": 0.55,
                "40": 0.52,
                "45": 0.47,
                "50": 0.4,
                "55": 0.31,
                "60": null,
                "65": null
            },
            "-10": {
                "15": 0.56,
                "20": 0.57,
                "25": 0.58,
                "30": 0.57,
                "35": 0.56,
                "40": 0.54,
                "45": 0.5,
                "50": 0.44,
                "55": 0.36,
                "60": 0.3,
                "65": null
            },
            "-7": {
                "15": 0.55,
                "20": 0.57,
                "25": 0.58,
                "30": 0.58,
                "35": 0.58,
                "40": 0.56,
                "45": 0.47,
                "50": 0.48,
                "55": 0.43,
                "60": 0.33,
                "65": null
            },
            "-2": {
                "15": 0.54,
                "20": 0.56,
                "25": 0.57,
                "30": 0.58,
                "35": 0.59,
                "40": 0.59,
                "45": 0.57,
                "50": 0.54,
                "55": 0.5,
                "60": 0.43,
                "65": null
            },
            "2": {
                "15": 0.54,
                "20": 0.55,
                "25": 0.56,
                "30": 0.58,
                "35": 0.62,
                "40": 0.6,
                "45": 0.54,
                "50": 0.58,
                "55": 0.55,
                "60": 0.5,
                "65": 0.43
            },
            "7": {
                "15": 0.57,
                "20": 0.54,
                "25": 0.55,
                "30": 0.57,
                "35": 0.65,
                "40": 0.6,
                "45": 0.61,
                "50": 0.61,
                "55": 0.64,
                "60": 0.57,
                "65": 0.52
            },
            "10": {
                "15": 0.65,
                "20": 0.55,
                "25": 0.55,
                "30": 0.56,
                "35": 0.61,
                "40": 0.6,
                "45": 0.64,
                "50": 0.62,
                "55": 0.64,
                "60": 0.6,
                "65": 0.57
            },
            "12": {
                "15": null,
                "20": 0.57,
                "25": 0.55,
                "30": 0.56,
                "35": 0.57,
                "40": 0.6,
                "45": 0.64,
                "50": 0.62,
                "55": 0.64,
                "60": 0.61,
                "65": 0.59
            },
            "15": {
                "15": null,
                "20": 0.66,
                "25": 0.56,
                "30": 0.55,
                "35": 0.57,
                "40": 0.59,
                "45": 0.61,
                "50": 0.63,
                "55": 0.64,
                "60": 0.63,
                "65": 0.62
            },
            "20": {
                "15": null,
                "20": null,
                "25": 0.66,
                "30": 0.56,
                "35": 0.51,
                "40": 0.58,
                "45": 0.59,
                "50": 0.62,
                "55": 0.63,
                "60": 0.65,
                "65": 0.66
            },
            "25": {
                "15": null,
                "20": null,
                "25": null,
                "30": 0.67,
                "35": 0.57,
                "40": 0.57,
                "45": 0.59,
                "50": 0.61,
                "55": 0.64,
                "60": 0.66,
                "65": 0.68
            },
            "30": {
                "15": null,
                "20": null,
                "25": null,
                "30": null,
                "35": 0.68,
                "40": 0.58,
                "45": 0.58,
                "50": 0.6,
                "55": 0.63,
                "60": 0.66,
                "65": 0.68
            },
            "35": {
                "15": null,
                "20": null,
                "25": null,
                "30": null,
                "35": null,
                "40": 0.69,
                "45": 0.59,
                "50": 0.59,
                "55": 0.61,
                "60": 0.65,
                "65": 0.68
            }
        },
        "heatload": {
            "-20": {
                "15": 14.3,
                "20": 14.01,
                "25": 13.72,
                "30": 13.43,
                "35": 13.14,
                "40": 12.85,
                "45": 12.56,
                "50": 12.27,
                "55": 11.98,
                "60": null,
                "65": null
            },
            "-15": {
                "15": 20.82,
                "20": 19.87,
                "25": 18.92,
                "30": 17.97,
                "35": 17.02,
                "40": 16.07,
                "45": 15.12,
                "50": 14.17,
                "55": 13.22,
                "60": null,
                "65": null
            },
            "-12": {
                "15": 20.99,
                "20": 20.28,
                "25": 19.58,
                "30": 18.87,
                "35": 18.29,
                "40": 17.46,
                "45": 16.49,
                "50": 16.04,
                "55": 15.47,
                "60": null,
                "65": null
            },
            "-10": {
                "15": 22.47,
                "20": 21.75,
                "25": 21.03,
                "30": 20.31,
                "35": 19.7,
                "40": 18.87,
                "45": 17.91,
                "50": 17.43,
                "55": 16.82,
                "60": 15.98,
                "65": null
            },
            "-7": {
                "15": 24.93,
                "20": 23.89,
                "25": 22.85,
                "30": 21.81,
                "35": 21.2,
                "40": 19.73,
                "45": 17.84,
                "50": 17.65,
                "55": 17.04,
                "60": 15.57,
                "65": null
            },
            "-2": {
                "15": 28.38,
                "20": 27.6,
                "25": 26.83,
                "30": 26.05,
                "35": 25.33,
                "40": 24.5,
                "45": 23.62,
                "50": 22.95,
                "55": 22.23,
                "60": 21.41,
                "65": null
            },
            "2": {
                "15": 29.01,
                "20": 28.27,
                "25": 27.53,
                "30": 26.8,
                "35": 26.4,
                "40": 25.32,
                "45": 23.9,
                "50": 23.85,
                "55": 23.45,
                "60": 22.37,
                "65": 21.63
            },
            "7": {
                "15": 35.4,
                "20": 34.5,
                "25": 33.6,
                "30": 32.7,
                "35": 31.9,
                "40": 30.9,
                "45": 29.79,
                "50": 29.1,
                "55": 28.3,
                "60": 27.3,
                "65": 26.4
            },
            "10": {
                "15": 36.62,
                "20": 35.89,
                "25": 35.17,
                "30": 34.44,
                "35": 33.6,
                "40": 32.99,
                "45": 32.5,
                "50": 31.54,
                "55": 30.7,
                "60": 30.09,
                "65": 29.37
            },
            "12": {
                "15": null,
                "20": 37.53,
                "25": 36.8,
                "30": 36.08,
                "35": 35.0,
                "40": 34.63,
                "45": 34.6,
                "50": 33.18,
                "55": 32.1,
                "60": 31.73,
                "65": 31.0
            },
            "15": {
                "15": null,
                "20": 40.05,
                "25": 39.16,
                "30": 38.27,
                "35": 37.3,
                "40": 36.49,
                "45": 35.75,
                "50": 34.71,
                "55": 33.74,
                "60": 32.93,
                "65": 32.04
            },
            "20": {
                "15": null,
                "20": null,
                "25": 44.17,
                "30": 43.17,
                "35": 42.0,
                "40": 41.17,
                "45": 40.5,
                "50": 39.17,
                "55": 38.0,
                "60": 37.17,
                "65": 36.17
            },
            "25": {
                "15": null,
                "20": null,
                "25": null,
                "30": 45.45,
                "35": 44.34,
                "40": 43.53,
                "45": 42.89,
                "50": 41.62,
                "55": 40.5,
                "60": 39.7,
                "65": 38.74
            },
            "30": {
                "15": null,
                "20": null,
                "25": null,
                "30": null,
                "35": 47.86,
                "40": 47.06,
                "45": 46.45,
                "50": 45.07,
                "55": 43.89,
                "60": 43.09,
                "65": 42.1
            },
            "35": {
                "15": null,
                "20": null,
                "25": null,
                "30": null,
                "35": null,
                "40": 50.58,
                "45": 50.02,
                "50": 48.53,
                "55": 47.27,
                "60": 46.48,
                "65": 45.45
            }
        },
        "ids": {
            "-20": {
                "15": 1,
                "20": 2,
                "25": 3,
                "30": 4,
                "35": 5,
                "40": 6,
                "45": 7,
                "50": 8,
                "55": 9,
                "60": 10,
                "65": 11
            },
            "-15": {
                "15": 12,
                "20": 13,
                "25": 14,
                "30": 15,
                "35": 16,
                "40": 17,
                "45": 18,
                "50": 19,
                "55": 20,
                "60": 21,
                "65": 22
            },
            "-12": {
                "15": 23,
                "20": 24,
                "25": 25,
                "30": 26,
                "35": 27,
                "40": 28,
                "45": 29,
                "50": 30,
                "55": 31,
                "60": 32,
                "65": 33
            },
            "-10": {
                "15": 34,
                "20": 35,
                "25": 36,
                "30": 37,
                "35": 38,
                "40": 39,
                "45": 40,
                "50": 41,
                "55": 42,
                "60": 43,
                "65": 44
            },
            "-7": {
                "15": 45,
                "20": 46,
                "25": 47,
                "30": 48,
                "35": 49,
                "40": 50,
                "45": 51,
                "50": 52,
                "55": 53,
                "60": 54,
                "65": 55
            },
            "-2": {
                "15": 56,
                "20": 57,
                "25": 58,
                "30": 59,
                "35": 60,
                "40": 61,
                "45": 62,
                "50": 63,
                "55": 64,
                "60": 65,
                "65": 66
            },
            "2": {
                "15": 67,
                "20": 68,
                "25": 69,
                "30": 70,
                "35": 71,
                "40": 72,
                "45": 73,
                "50": 74,
                "55": 75,
                "60": 76,
                "65": 77
            },
            "7": {
                "15": 78,
                "20": 79,
                "25": 80,
                "30": 81,
                "35": 82,
                "40": 83,
                "45": 84,
                "50": 85,
                "55": 86,
                "60": 87,
                "65": 88
            },
            "10": {
                "15": 89,
                "20": 90,
                "25": 91,
                "30": 92,
                "35": 93,
                "40": 94,
                "45": 95,
                "50": 96,
                "55": 97,
                "60": 98,
                "65": 99
            },
            "12": {
                "15": 100,
                "20": 101,
                "25": 102,
                "30": 103,
                "35": 104,
                "40": 105,
                "45": 106,
                "50": 107,
                "55": 108,
                "60": 109,
                "65": 110
            },
            "15": {
                "15": 111,
                "20": 112,
                "25": 113,
                "30": 114,
                "35": 115,
                "40": 116,
                "45": 117,
                "50": 118,
                "55": 119,
                "60": 120,
                "65": 121
            },
            "20": {
                "15": 122,
                "20": 123,
                "25": 124,
                "30": 125,
                "35": 126,
                "40": 127,
                "45": 128,
                "50": 129,
                "55": 130,
                "60": 131,
                "65": 132
            },
            "25": {
                "15": 133,
                "20": 134,
                "25": 135,
                "30": 136,
                "35": 137,
                "40": 138,
                "45": 139,
                "50": 140,
                "55": 141,
                "60": 142,
                "65": 143
            },
            "30": {
                "15": 144,
                "20": 145,
                "25": 146,
                "30": 147,
                "35": 148,
                "40": 149,
                "45": 150,
                "50": 151,
                "55": 152,
                "60": 153,
                "65": 154
            },
            "35": {
                "15": 155,
                "20": 156,
                "25": 157,
                "30": 158,
                "35": 159,
                "40": 160,
                "45": 161,
                "50": 162,
                "55": 163,
                "60": 164,
                "65": 165
            }
        },
        "min_heatload": 11980.0,
        "max_heatload": 50580.0
    },
    "Air_60kW": {
        "eta_s": {
            "-20": {
                "15": 0.57,
                "20": 0.57,
                "25": 0.56,
                "30": 0.53,
                "35": 0.43,
                "40": 0.43,
                "45": 0.38,
                "50": 0.3,
                "55": 0.3,
                "60": null,
                "65": null
            },
            "-15": {
                "15": 0.57,
                "20": 0.58,
                "25": 0.58,
                "30": 0.57,
                "35": 0.5,
                "40": 0.5,
                "45": 0.48,
                "50": 0.37,
                "55": 0.44,
                "60": null,
                "65": null
            },
            "-12": {
                "15": 0.56,
                "20": 0.57,
                "25": 0.58,
                "30": 0.58,
                "35": 0.56,
                "40": 0.53,
                "45": 0.49,
                "50": 0.42,
                "55": 0.33,
                "60": null,
                "65": null
            },
            "-10": {
                "15": 0.55,
                "20": 0.57,
                "25": 0.58,
                "30": 0.58,
                "35": 0.57,
                "40": 0.55,
                "45": 0.51,
                "50": 0.46,
                "55": 0.38,
                "60": 0.3,
                "65": null
            },
            "-7": {
                "15": 0.54,
                "20": 0.56,
                "25": 0.58,
                "30": 0.59,
                "35": 0.58,
                "40": 0.57,
                "45": 0.56,
                "50": 0.5,
                "55": 0.59,
                "60": 0.35,
                "65": null
            },
            "-2": {
                "15": 0.52,
                "20": 0.54,
                "25": 0.57,
                "30": 0.59,
                "35": 0.6,
                "40": 0.6,
                "45": 0.58,
                "50": 0.56,
                "55": 0.52,
                "60": 0.45,
                "65": null
            },
            "2": {
                "15": 0.5,
                "20": 0.53,
                "25": 0.55,
                "30": 0.58,
                "35": 0.62,
                "40": 0.6,
                "45": 0.61,
                "50": 0.59,
                "55": 0.62,
                "60": 0.52,
                "65": 0.45
            },
            "7": {
                "15": 0.49,
                "20": 0.5,
                "25": 0.53,
                "30": 0.56,
                "35": 0.63,
                "40": 0.6,
                "45": 0.64,
                "50": 0.62,
                "55": 0.63,
                "60": 0.58,
                "65": 0.54
            },
            "10": {
                "15": 0.53,
                "20": 0.5,
                "25": 0.52,
                "30": 0.55,
                "35": 0.59,
                "40": 0.6,
                "45": 0.64,
                "50": 0.63,
                "55": 0.67,
                "60": 0.61,
                "65": 0.58
            },
            "12": {
                "15": null,
                "20": 0.5,
                "25": 0.51,
                "30": 0.54,
                "35": 0.55,
                "40": 0.59,
                "45": 0.61,
                "50": 0.63,
                "55": 0.66,
                "60": 0.62,
                "65": 0.6
            },
            "15": {
                "15": null,
                "20": 0.53,
                "25": 0.5,
                "30": 0.52,
                "35": 0.55,
                "40": 0.58,
                "45": 0.61,
                "50": 0.63,
                "55": 0.64,
                "60": 0.64,
                "65": 0.63
            },
            "20": {
                "15": null,
                "20": null,
                "25": 0.54,
                "30": 0.5,
                "35": 0.5,
                "40": 0.56,
                "45": 0.59,
                "50": 0.62,
                "55": 0.65,
                "60": 0.66,
                "65": 0.66
            },
            "25": {
                "15": null,
                "20": null,
                "25": null,
                "30": 0.54,
                "35": 0.51,
                "40": 0.53,
                "45": 0.57,
                "50": 0.6,
                "55": 0.63,
                "60": 0.66,
                "65": 0.68
            },
            "30": {
                "15": null,
                "20": null,
                "25": null,
                "30": null,
                "35": 0.55,
                "40": 0.51,
                "45": 0.54,
                "50": 0.58,
                "55": 0.62,
                "60": 0.65,
                "65": 0.68
            },
            "35": {
                "15": null,
                "20": null,
                "25": null,
                "30": null,
                "35": null,
                "40": 0.55,
                "45": 0.52,
                "50": 0.55,
                "55": 0.59,
                "60": 0.63,
                "65": 0.67
            }
        },
        "heatload": {
            "-20": {
                "15": 25.5,
                "20": 25.0,
                "25": 24.5,
                "30": 24.0,
                "35": 23.5,
                "40": 23.0,
                "45": 22.51,
                "50": 22.0,
                "55": 21.5,
                "60": null,
                "65": null
            },
            "-15": {
                "15": 31.88,
                "20": 31.22,
                "25": 30.57,
                "30": 29.91,
                "35": 29.34,
                "40": 28.59,
                "45": 27.76,
                "50": 27.28,
                "55": 26.71,
                "60": null,
                "65": null
            },
            "-12": {
                "15": 36.21,
                "20": 35.42,
                "25": 34.62,
                "30": 33.83,
                "35": 33.13,
                "40": 32.24,
                "45": 31.26,
                "50": 30.66,
                "55": 29.96,
                "60": null,
                "65": null
            },
            "-10": {
                "15": 39.13,
                "20": 38.31,
                "25": 37.5,
                "30": 36.68,
                "35": 35.96,
                "40": 35.05,
                "45": 34.05,
                "50": 33.42,
                "55": 32.7,
                "60": 31.79,
                "65": null
            },
            "-7": {
                "15": 43.98,
                "20": 42.76,
                "25": 41.53,
                "30": 40.31,
                "35": 39.2,
                "40": 37.86,
                "45": 36.4,
                "50": 35.41,
                "55": 34.3,
                "60": 32.96,
                "65": null
            },
            "-2": {
                "15": 50.79,
                "20": 49.89,
                "25": 48.98,
                "30": 48.08,
                "35": 47.26,
                "40": 46.27,
                "45": 45.19,
                "50": 44.47,
                "55": 43.65,
                "60": 42.66,
                "65": null
            },
            "2": {
                "15": 53.69,
                "20": 52.71,
                "25": 51.73,
                "30": 50.74,
                "35": 50.0,
                "40": 48.78,
                "45": 47.32,
                "50": 46.81,
                "55": 46.07,
                "60": 44.85,
                "65": 43.87
            },
            "7": {
                "15": 65.02,
                "20": 63.74,
                "25": 62.47,
                "30": 61.19,
                "35": 60.1,
                "40": 58.64,
                "45": 57.0,
                "50": 56.09,
                "55": 55.0,
                "60": 53.54,
                "65": 52.27
            },
            "10": {
                "15": 68.45,
                "20": 67.43,
                "25": 66.4,
                "30": 65.38,
                "35": 64.6,
                "40": 63.33,
                "45": 61.8,
                "50": 61.28,
                "55": 60.5,
                "60": 59.23,
                "65": 58.2
            },
            "12": {
                "15": null,
                "20": 68.42,
                "25": 67.67,
                "30": 66.92,
                "35": 66.0,
                "40": 65.42,
                "45": 65.0,
                "50": 63.92,
                "55": 63.0,
                "60": 62.42,
                "65": 61.67
            },
            "15": {
                "15": null,
                "20": 74.48,
                "25": 73.39,
                "30": 72.3,
                "35": 71.28,
                "40": 70.12,
                "45": 68.88,
                "50": 67.94,
                "55": 66.92,
                "60": 65.75,
                "65": 64.66
            },
            "20": {
                "15": null,
                "20": null,
                "25": 82.89,
                "30": 81.8,
                "35": 80.68,
                "40": 79.62,
                "45": 78.6,
                "50": 77.45,
                "55": 76.33,
                "60": 75.27,
                "65": 74.19
            },
            "25": {
                "15": null,
                "20": null,
                "25": null,
                "30": 86.55,
                "35": 85.41,
                "40": 84.14,
                "45": 82.82,
                "50": 81.74,
                "55": 80.6,
                "60": 79.34,
                "65": 78.14
            },
            "30": {
                "15": null,
                "20": null,
                "25": null,
                "30": null,
                "35": 92.47,
                "40": 91.16,
                "45": 89.78,
                "50": 88.65,
                "55": 87.45,
                "60": 86.13,
                "65": 84.88
            },
            "35": {
                "15": null,
                "20": null,
                "25": null,
                "30": null,
                "35": null,
                "40": 98.17,
                "45": 96.75,
                "50": 95.55,
                "55": 94.29,
                "60": 92.93,
                "65": 91.61
            }
        },
        "ids": {
            "-20": {
                "15": 1,
                "20": 2,
                "25": 3,
                "30": 4,
                "35": 5,
                "40": 6,
                "45": 7,
                "50": 8,
                "55": 9,
                "60": 10,
                "65": 11
            },
            "-15": {
                "15": 12,
                "20": 13,
                "25": 14,
                "30": 15,
                "35": 16,
                "40": 17,
                "45": 18,
                "50": 19,
                "55": 20,
                "60": 21,
                "65": 22
            },
            "-12": {
                "15": 23,
                "20": 24,
                "25": 25,
                "30": 26,
                "35": 27,
                "40": 28,
                "45": 29,
                "50": 30,
                "55": 31,
                "60": 32,
                "65": 33
            },
            "-10": {
                "15": 34,
                "20": 35,
                "25": 36,
                "30": 37,
                "35": 38,
                "40": 39,
                "45": 40,
                "50": 41,
                "55": 42,
                "60": 43,
                "65": 44
            },
            "-7": {
                "15": 45,
                "20": 46,
                "25": 47,
                "30": 48,
                "35": 49,
                "40": 50,
                "45": 51,
                "50": 52,
                "55": 53,
                "60": 54,
                "65": 55
            },
            "-2": {
                "15": 56,
                "20": 57,
                "25": 58,
                "30": 59,
                "35": 60,
                "40": 61,
                "45": 62,
                "50": 63,
                "55": 64,
                "60": 65,
                "65": 66
            },
            "2": {
                "15": 67,
                "20": 68,
                "25": 69,
                "30": 70,
                "35": 71,
                "40": 72,
                "45": 73,
                "50": 74,
                "55": 75,
                "60": 76,
                "65": 77
            },
            "7": {
                "15": 78,
                "20": 79,
                "25": 80,
                "30": 81,
                "35": 82,
                "40": 83,
                "45": 84,
                "50": 85,
                "55": 86,
                "60": 87,
                "65": 88
            },
            "10": {
                "15": 89,
                "20": 90,
                "25": 91,
                "30": 92,
                "35": 93,
                "40": 94,
                "45": 95,
                "50": 96,
                "55": 97,
                "60": 98,
                "65": 99
            },
            "12": {
                "15": 100,
                "20": 101,
                "25": 102,
                "30": 103,
                "35": 104,
                "40": 105,
                "45": 106,
                "50": 107,
                "55": 108,
                "60": 109,
                "65": 110
            },
            "15": {
                "15": 111,
                "20": 112,
                "25": 113,
                "30": 114,
                "35": 115,
                "40": 116,
                "45": 117,
                "50": 118,
                "55": 119,
                "60": 120,
                "65": 121
            },
            "20": {
                "15": 122,
                "20": 123,
                "25": 124,
                "30": 125,
                "35": 126,
                "40": 127,
                "45": 128,
                "50": 129,
                "55": 130,
                "60": 131,
                "65": 132
            },
            "25": {
                "15": 133,
                "20": 134,
                "25": 135,
                "30": 136,
                "35": 137,
                "40": 138,
                "45": 139,
                "50": 140,
                "55": 141,
                "60": 142,
                "65": 143
            },
            "30": {
                "15": 144,
                "20": 145,
                "25": 146,
                "30": 147,
                "35": 148,
                "40": 149,
                "45": 150,
                "50": 151,
                "55": 152,
                "60": 153,
                "65": 154
            },
            "35": {
                "15": 155,
                "20": 156,
                "25": 157,
                "30": 158,
                "35": 159,
                "40": 160,
                "45": 161,
                "50": 162,
                "55": 163,
                "60": 164,
                "65": 165
            }
        },
        "min_heatload": 21500.0,
        "max_heatload": 98170.0
    }
}